sqlalchemy_bulk_lazy_loader.py
SQLAlchemy_bulk_lazy_loader-0.9.9.dist-info/DESCRIPTION.rst
SQLAlchemy_bulk_lazy_loader-0.9.9.dist-info/METADATA
SQLAlchemy_bulk_lazy_loader-0.9.9.dist-info/RECORD
SQLAlchemy_bulk_lazy_loader-0.9.9.dist-info/WHEEL
SQLAlchemy_bulk_lazy_loader-0.9.9.dist-info/metadata.json
SQLAlchemy_bulk_lazy_loader-0.9.9.dist-info/top_level.txt
