Metadata-Version: 2.0
Name: SQLAlchemy-bulk-lazy-loader
Version: 0.9.9
Summary: A Bulk Lazy Loader for Sqlalchemy that solves the n + 1 loading problem
Home-page: https://github.com/operator/sqlalchemy_bulk_lazy_loader
Author: Operator Inc
Author-email: chanind@operator.com
License: MIT
Keywords: sqlalchemy orm lazyload joinedload subqueryload
Platform: UNKNOWN
Classifier: Intended Audience :: Developers
Classifier: Topic :: Database :: Front-Ends
Classifier: Operating System :: OS Independent
Classifier: License :: OSI Approved :: MIT License
Classifier: Programming Language :: Python :: 3
Requires-Dist: SQLAlchemy (>=1.0)
